amxfirmware/__init__.py
amxfirmware-0.0.5.dist-info/LICENSE
amxfirmware-0.0.5.dist-info/METADATA
amxfirmware-0.0.5.dist-info/WHEEL
amxfirmware-0.0.5.dist-info/top_level.txt
amxfirmware-0.0.5.dist-info/RECORD
