Metadata-Version: 2.1
Name: amxfirmware
Version: 0.0.5
Summary: amx telnet info, firmware checks, logs, etc.
Home-page: https://github.com/logantv/amxfirmware
Author: Logan Vaughn
License: UNKNOWN
Project-URL: Bug Tracker, https://github.com/logantv/amxfirmware/issues
Platform: UNKNOWN
Classifier: Programming Language :: Python :: 3
Classifier: License :: OSI Approved :: MIT License
Classifier: Operating System :: OS Independent
Requires-Python: >=3.6
